d3mdm/__init__.py
d3mdm/__main__.py
d3mdm/d3m.py
d3mdm/local.py
d3mdm/s3.py
d3mdm/splitter.py
d3m_dataset_manager-0.1.0.dist-info/AUTHORS.rst
d3m_dataset_manager-0.1.0.dist-info/LICENSE
d3m_dataset_manager-0.1.0.dist-info/METADATA
d3m_dataset_manager-0.1.0.dist-info/WHEEL
d3m_dataset_manager-0.1.0.dist-info/entry_points.txt
d3m_dataset_manager-0.1.0.dist-info/top_level.txt
d3m_dataset_manager-0.1.0.dist-info/RECORD
