Metadata-Version: 2.1
Name: d3m-dataset-manager
Version: 0.1.0
Summary: Command line tool and python package to generate and manage datasets in the D3M format.
Home-page: https://github.com/HDI-Project/d3m-dataset-manager
Author: MIT Data To AI Lab
Author-email: dailabmit@gmail.com
License: MIT license
Keywords: d3mdm d3m-dataset-manager D3M Dataset Manager
Platform: UNKNOWN
Classifier: Development Status :: 2 - Pre-Alpha
Classifier: Intended Audience :: Developers
Classifier: License :: OSI Approved :: MIT License
Classifier: Natural Language :: English
Classifier: Programming Language :: Python :: 3
Classifier: Programming Language :: Python :: 3.4
Classifier: Programming Language :: Python :: 3.5
Classifier: Programming Language :: Python :: 3.6
Classifier: Programming Language :: Python :: 3.7
Requires-Python: >=3.4
Requires-Dist: bs4 (>=0.0.1)
Requires-Dist: pandas (>=0.22.0)
Requires-Dist: requests (>=2.18.4)
Requires-Dist: boto3 (>=1.5.22)
Requires-Dist: scikit-learn (>=0.21.2)
Provides-Extra: dev
Requires-Dist: bumpversion (>=0.5.3) ; extra == 'dev'
Requires-Dist: pip (>=9.0.1) ; extra == 'dev'
Requires-Dist: watchdog (>=0.8.3) ; extra == 'dev'
Requires-Dist: m2r (>=0.2.0) ; extra == 'dev'
Requires-Dist: Sphinx (>=1.7.1) ; extra == 'dev'
Requires-Dist: sphinx-rtd-theme (>=0.2.4) ; extra == 'dev'
Requires-Dist: autodocsumm (>=0.1.10) ; extra == 'dev'
Requires-Dist: flake8 (>=3.7.7) ; extra == 'dev'
Requires-Dist: isort (>=4.3.4) ; extra == 'dev'
Requires-Dist: autoflake (>=1.2) ; extra == 'dev'
Requires-Dist: autopep8 (>=1.4.3) ; extra == 'dev'
Requires-Dist: twine (>=1.10.0) ; extra == 'dev'
Requires-Dist: wheel (>=0.30.0) ; extra == 'dev'
Requires-Dist: coverage (>=4.5.1) ; extra == 'dev'
Requires-Dist: tox (>=2.9.1) ; extra == 'dev'
Requires-Dist: pytest (>=3.4.2) ; extra == 'dev'
Requires-Dist: pytest-cov (>=2.6.0) ; extra == 'dev'
Provides-Extra: test
Requires-Dist: pytest (>=3.4.2) ; extra == 'test'
Requires-Dist: pytest-cov (>=2.6.0) ; extra == 'test'
